records.py
records-0.6.0.dist-info/LICENSE
records-0.6.0.dist-info/METADATA
records-0.6.0.dist-info/WHEEL
records-0.6.0.dist-info/entry_points.txt
records-0.6.0.dist-info/top_level.txt
records-0.6.0.dist-info/RECORD
